noma/__init__.py
noma/bitcoind.py
noma/config.py
noma/install.py
noma/lnd.py
noma/node.py
noma/noma.py
noma/rpcauth.py
noma/usb.py
noma-0.5.1.dist-info/LICENSE
noma-0.5.1.dist-info/METADATA
noma-0.5.1.dist-info/WHEEL
noma-0.5.1.dist-info/entry_points.txt
noma-0.5.1.dist-info/top_level.txt
noma-0.5.1.dist-info/zip-safe
noma-0.5.1.dist-info/RECORD
