Metadata-Version: 2.1
Name: noma
Version: 0.5.1
Summary: bitcoin lightning node management tool
Home-page: http://github.com/lncm/noma
Author: LNCM Contributors
Author-email: lncm@protonmail.com
License: Apache 2.0
Keywords: bitcoin lightning node
Platform: UNKNOWN
Requires-Dist: psutil
Requires-Dist: docopt
Requires-Dist: requests
Requires-Dist: docker-compose
